[
  {
    "category": "pages",
    "pages": [
      {
        "pageId": "main",
        "folder": "main",
        "L1": "MAIN",
        "L2": "",
        "L3": "",
        "L4": "",
        "date": "",
        "status": 1,
        "complete": true,
        "memo": ""
      },
      {
        "pageId": "CEO",
        "folder": "intro",
        "L1": "우진 I&S",
        "L2": "인사말",
        "L3": "",
        "L4": "",
        "date": "",
        "status": 0,
        "complete": true,
        "memo": ""
      },
      {
        "pageId": "intro_company",
        "folder": "intro",
        "L1": "우진 I&S",
        "L2": "기업소개",
        "L3": "기업 개요",
        "L4": "",
        "date": "",
        "status": 0,
        "complete": true,
        "memo": ""
      },
      {
        "pageId": "ORG",
        "folder": "intro",
        "L1": "우진 I&S",
        "L2": "기업소개",
        "L3": "조직도",
        "L4": "",
        "date": "",
        "status": 0,
        "complete": true,
        "memo": ""
      },
      {
        "pageId": "vision",
        "folder": "intro",
        "L1": "우진 I&S",
        "L2": "기업소개",
        "L3": "가치 체계",
        "L4": "",
        "date": "",
        "status": 0,
        "complete": true,
        "memo": ""
      },
      {
        "pageId": "history",
        "folder": "intro",
        "L1": "우진 I&S",
        "L2": "기업소개",
        "L3": "WJ 히스토리",
        "L4": "",
        "date": "",
        "status": 0,
        "complete": true,
        "memo": ""
      },
      {
        "pageId": "CI",
        "folder": "intro",
        "L1": "우진 I&S",
        "L2": "C I / 서체",
        "L3": "",
        "L4": "",
        "date": "",
        "status": 0,
        "complete": true,
        "memo": ""
      },
      {
        "pageId": "location",
        "folder": "intro",
        "L1": "우진 I&S",
        "L2": "찾아오시는 길",
        "L3": "",
        "L4": "",
        "date": "",
        "status": 0,
        "complete": true,
        "memo": ""
      },
      {
        "pageId": "facility_part",
        "folder": "business",
        "L1": "사업분야",
        "L2": "설비 부문",
        "L3": "메인",
        "L4": "",
        "date": "",
        "status": 0,
        "complete": true,
        "memo": ""
      },
      {
        "pageId": "facility_machine",
        "folder": "business",
        "L1": "사업분야",
        "L2": "설비 부문",
        "L3": "기계 및 소화 설비",
        "L4": "",
        "date": "",
        "status": 0,
        "complete": true,
        "memo": ""
      },
      {
        "pageId": "facility_P.F.P",
        "folder": "business",
        "L1": "사업분야",
        "L2": "설비 부문",
        "L3": "P.F.P. SYSTEM",
        "L4": "",
        "date": "",
        "status": 0,
        "complete": true,
        "memo": ""
      },
      {
        "pageId": "facility_IDC",
        "folder": "business",
        "L1": "사업분야",
        "L2": "설비 부문",
        "L3": "IDC 차별화 공법",
        "L4": "",
        "date": "",
        "status": 0,
        "complete": true,
        "memo": ""
      },
      {
        "pageId": "product_coating",
        "folder": "business",
        "L1": "사업분야",
        "L2": "제조 부문",
        "L3": "불소수지 코팅",
        "L4": "분체도장 (Coating)",
        "date": "",
        "status": 0,
        "complete": true,
        "memo": ""
      },
      {
        "pageId": "product_lining",
        "folder": "business",
        "L1": "사업분야",
        "L2": "제조 부문",
        "L3": "",
        "L4": "회전성형 (Lining)",
        "date": "",
        "status": 0,
        "complete": true,
        "memo": ""
      },
      {
        "pageId": "product_hook",
        "folder": "business",
        "L1": "사업분야",
        "L2": "제조 부문",
        "L3": "HOOK-UP PIPE & FITTING",
        "L4": "",
        "date": "",
        "status": 0,
        "complete": true,
        "memo": ""
      },
      {
        "pageId": "module",
        "folder": "RND",
        "L1": "사업분야",
        "L2": "연구 개발(R&D) 부문",
        "L3": "모듈화 배관",
        "L4": "",
        "date": "",
        "status": 0,
        "complete": true,
        "memo": ""
      },
      {
        "pageId": "system",
        "folder": "RND",
        "L1": "사업분야",
        "L2": "연구 개발(R&D) 부문",
        "L3": "시스템 덕트",
        "L4": "",
        "date": "",
        "status": 0,
        "complete": true,
        "memo": ""
      },
      {
        "pageId": "newEnergy",
        "folder": "RND",
        "L1": "사업분야",
        "L2": "연구 개발(R&D) 부문",
        "L3": "신재생에너지 활용 기술 연구",
        "L4": "",
        "date": "",
        "status": 0,
        "complete": true,
        "memo": ""
      },
      {
        "pageId": "mediaHub_social",
        "folder": "media",
        "L1": "홍보센터",
        "L2": "미디어 허브",
        "L3": "소셜미디어",
        "L4": "",
        "date": "",
        "status": 0,
        "complete": true,
        "memo": ""
      },
      {
        "pageId": "mediaHub_news",
        "folder": "media",
        "L1": "홍보센터",
        "L2": "미디어 허브",
        "L3": "뉴스",
        "L4": "목록",
        "date": "",
        "status": 0,
        "complete": true,
        "memo": ""
      },
      {
        "pageId": "mediaHub_board",
        "folder": "media",
        "L1": "홍보센터",
        "L2": "미디어 허브",
        "L3": "뉴스",
        "L4": "상세보기",
        "date": "",
        "status": 0,
        "complete": true,
        "memo": ""
      },
      {
        "pageId": "center",
        "folder": "media",
        "L1": "홍보센터",
        "L2": "미디어 허브",
        "L3": "안전보건소식지",
        "L4": "",
        "date": "",
        "status": 0,
        "complete": true,
        "memo": ""
      },
      {
        "pageId": "ourwork_facility",
        "folder": "ourwork",
        "L1": "홍보센터",
        "L2": "Our Work",
        "L3": "설비 부문실적",
        "L4": "주요실적",
        "date": "",
        "status": 0,
        "complete": true,
        "memo": ""
      },
      {
        "pageId": "ourwork_manufacturing",
        "folder": "ourwork",
        "L1": "홍보센터",
        "L2": "Our Work",
        "L3": "설비 부문실적",
        "L4": "전체실적",
        "date": "",
        "status": 0,
        "complete": true,
        "memo": ""
      },
      {
        "pageId": "ourwork_product",
        "folder": "ourwork",
        "L1": "홍보센터",
        "L2": "Our Work",
        "L3": "제조 부문실적",
        "L4": "주요실적",
        "date": "",
        "status": 0,
        "complete": true,
        "memo": ""
      },
      {
        "pageId": "ourwork_product_score",
        "folder": "ourwork",
        "L1": "홍보센터",
        "L2": "Our Work",
        "L3": "제조 부문실적",
        "L4": "전체실적",
        "date": "",
        "status": 0,
        "complete": true,
        "memo": ""
      },
      {
        "pageId": "certification",
        "folder": "certifications",
        "L1": "홍보센터",
        "L2": "자격 및 수상",
        "L3": "국내 및 해외 인증",
        "L4": "",
        "date": "",
        "status": 0,
        "complete": true,
        "memo": ""
      },
      {
        "pageId": "domestic",
        "folder": "certifications",
        "L1": "홍보센터",
        "L2": "자격 및 수상",
        "L3": "특허 및 면허",
        "L4": "",
        "date": "",
        "status": 0,
        "complete": true,
        "memo": ""
      },
      {
        "pageId": "awards",
        "folder": "certifications",
        "L1": "홍보센터",
        "L2": "자격 및 수상",
        "L3": "Awards",
        "L4": "주요 내용",
        "date": "",
        "status": 0,
        "complete": true,
        "memo": ""
      },
      {
        "pageId": "awards_all",
        "folder": "certifications",
        "L1": "홍보센터",
        "L2": "자격 및 수상",
        "L3": "",
        "L4": "전체 내용",
        "date": "",
        "status": 0,
        "complete": true,
        "memo": ""
      },
      {
        "pageId": "ESG",
        "folder": "business",
        "L1": "지속가능경영",
        "L2": "ESG경영",
        "L3": "",
        "L4": "",
        "date": "",
        "status": 0,
        "complete": true,
        "memo": ""
      },
      {
        "pageId": "safety",
        "folder": "business",
        "L1": "지속가능경영",
        "L2": "안전 · 보건 · 환경",
        "L3": "",
        "L4": "",
        "date": "",
        "status": 0,
        "complete": true,
        "memo": ""
      },
      {
        "pageId": "substain_ESG",
        "folder": "SustainabilityManagement",
        "L1": "지속가능경영",
        "L2": "평가보고서",
        "L3": "ESG 평가보고서",
        "L4": "",
        "date": "",
        "status": 0,
        "complete": true,
        "memo": ""
      },
      {
        "pageId": "substain_SH",
        "folder": "SustainabilityManagement",
        "L1": "지속가능경영",
        "L2": "평가보고서",
        "L3": "SH 평가보고서",
        "L4": "",
        "date": "",
        "status": 0,
        "complete": true,
        "memo": ""
      },
      {
        "pageId": "substain_manage",
        "folder": "SustainabilityManagement",
        "L1": "지속가능경영",
        "L2": "윤리경영",
        "L3": "",
        "L4": "",
        "date": "",
        "status": 0,
        "complete": true,
        "memo": ""
      },
      {
        "pageId": "quality",
        "folder": "business",
        "L1": "지속가능경영",
        "L2": "품질경영",
        "L3": "",
        "L4": "",
        "date": "",
        "status": 0,
        "complete": true,
        "memo": ""
      },
      {
        "pageId": "ESG_social",
        "folder": "business",
        "L1": "지속가능경영",
        "L2": "사회공헌",
        "L3": "",
        "L4": "",
        "date": "",
        "status": 0,
        "complete": true,
        "memo": ""
      },
      {
        "pageId": "dart",
        "folder": "investment",
        "L1": "투자 정보",
        "L2": "공시정보",
        "L3": "기업공시",
        "L4": "",
        "date": "",
        "status": 0,
        "complete": true,
        "memo": ""
      },
      {
        "pageId": "announcement",
        "folder": "investment",
        "L1": "투자 정보",
        "L2": "공시정보",
        "L3": "전자공고",
        "L4": "",
        "date": "",
        "status": 0,
        "complete": true,
        "memo": ""
      },
      {
        "pageId": "charter",
        "folder": "investment",
        "L1": "투자 정보",
        "L2": "공시정보",
        "L3": "정관",
        "L4": "",
        "date": "",
        "status": 0,
        "complete": true,
        "memo": ""
      },
      {
        "pageId": "charter_info",
        "folder": "investment",
        "L1": "투자 정보",
        "L2": "지배구조",
        "L3": "주주정보",
        "L4": "",
        "date": "",
        "status": 0,
        "complete": true,
        "memo": ""
      },
      {
        "pageId": "board_members",
        "folder": "investment",
        "L1": "투자 정보",
        "L2": "지배구조",
        "L3": "이사회",
        "L4": "",
        "date": "",
        "status": 0,
        "complete": true,
        "memo": ""
      },
      {
        "pageId": "audit_committee",
        "folder": "investment",
        "L1": "투자 정보",
        "L2": "지배구조",
        "L3": "감사기구",
        "L4": "",
        "date": "",
        "status": 0,
        "complete": true,
        "memo": ""
      },
      {
        "pageId": "org_eval",
        "folder": "investment",
        "L1": "투자 정보",
        "L2": "지배구조",
        "L3": "지배구조평가",
        "L4": "",
        "date": "",
        "status": 0,
        "complete": true,
        "memo": ""
      },
      {
        "pageId": "financial_info",
        "folder": "investment",
        "L1": "투자 정보",
        "L2": "재무정보",
        "L3": "요약 재무제표",
        "L4": "",
        "date": "",
        "status": 0,
        "complete": true,
        "memo": ""
      },
      {
        "pageId": "business_report",
        "folder": "investment",
        "L1": "투자 정보",
        "L2": "재무정보",
        "L3": "사업보고서",
        "L4": "",
        "date": "",
        "status": 0,
        "complete": true,
        "memo": ""
      },
      {
        "pageId": "audit_report",
        "folder": "investment",
        "L1": "투자 정보",
        "L2": "재무정보",
        "L3": "감사보고서",
        "L4": "",
        "date": "",
        "status": 0,
        "complete": true,
        "memo": ""
      },
      {
        "pageId": "credit_rating",
        "folder": "investment",
        "L1": "투자 정보",
        "L2": "재무정보",
        "L3": "재무제표",
        "L4": "",
        "date": "",
        "status": 0,
        "complete": true,
        "memo": ""
      },
      {
        "pageId": "https://finance.naver.com/item/main.nhn?code=010400 링크",
        "folder": "-",
        "L1": "투자 정보",
        "L2": "주가정보",
        "L3": "",
        "L4": "",
        "date": "",
        "status": 0,
        "complete": true,
        "memo": ""
      },
      {
        "pageId": "recruit",
        "folder": "recruitment",
        "L1": "채용",
        "L2": "인재상",
        "L3": "",
        "L4": "",
        "date": "",
        "status": 1,
        "complete": true,
        "memo": ""
      },
      {
        "pageId": "benefits",
        "folder": "recruitment",
        "L1": "채용",
        "L2": "복리후생",
        "L3": "",
        "L4": "",
        "date": "",
        "status": 0,
        "complete": true,
        "memo": ""
      },
      {
        "pageId": "employment",
        "folder": "recruitment",
        "L1": "채용",
        "L2": "채용안내",
        "L3": "",
        "L4": "",
        "date": "",
        "status": 0,
        "complete": true,
        "memo": ""
      },
      {
        "pageId": "FAQ",
        "folder": "FAQ",
        "L1": "Header",
        "L2": "고객지원",
        "L3": "상담문의",
        "L4": "",
        "date": "",
        "status": 0,
        "complete": true,
        "memo": ""
      },
      {
        "pageId": "application",
        "folder": "FAQ",
        "L1": "Header",
        "L2": "공사지명원",
        "L3": "공사지명원 요청",
        "L4": "",
        "date": "",
        "status": 0,
        "complete": true,
        "memo": ""
      },
      {
        "pageId": "application_submit",
        "folder": "FAQ",
        "L1": "Header",
        "L2": "공사지명원",
        "L3": "공사지명원 다운로드",
        "L4": "",
        "date": "",
        "status": 0,
        "complete": true,
        "memo": ""
      },
      {
        "pageId": "application_logIn",
        "folder": "FAQ",
        "L1": "Header",
        "L2": "공사지명원",
        "L3": "사이버신문고 안내",
        "L4": "",
        "date": "",
        "status": 0,
        "complete": true,
        "memo": ""
      },
      {
        "pageId": "feedback",
        "folder": "FAQ",
        "L1": "Header",
        "L2": "공사지명원",
        "L3": "사이버신문고 안내",
        "L4": "사이버신문고 템플릿",
        "date": "",
        "status": 0,
        "complete": true,
        "memo": ""
      },
      {
        "pageId": "feedback_submit",
        "folder": "FAQ",
        "L1": "Header",
        "L2": "언어변경",
        "L3": "사이버신문고 템플릿",
        "L4": "사이버신문고 템플릿",
        "date": "",
        "status": 0,
        "complete": true,
        "memo": ""
      },
      {
        "pageId": "sitemap",
        "folder": "footer",
        "L1": "Footer",
        "L2": "SITEMAP",
        "L3": "",
        "L4": "",
        "date": "",
        "status": 0,
        "complete": true,
        "memo": ""
      }
    ]
  }
]
